batch_ingestion_client_py/__init__.py
batch_ingestion_client_py/curl.py
batch_ingestion_client_py/data.py
batch_ingestion_client_py/lib.py
batch_ingestion_client_py/response.py
batch_ingestion_client_py-1.0.4.dist-info/LICENSE
batch_ingestion_client_py-1.0.4.dist-info/METADATA
batch_ingestion_client_py-1.0.4.dist-info/WHEEL
batch_ingestion_client_py-1.0.4.dist-info/top_level.txt
batch_ingestion_client_py-1.0.4.dist-info/RECORD
