Metadata-Version: 2.1
Name: batch-ingestion-client-py
Version: 1.0.4
Summary: A client for the BatchIngestion mediawiki API
Author: QuentinJanuel
Author-email: <quentinjanuelkij@gmail.com>
Keywords: python,mediawiki,batchingestion,wikidata,wikibase,api,client
Classifier: Development Status :: 1 - Planning
Classifier: Intended Audience :: Developers
Classifier: Programming Language :: Python :: 3
Classifier: Operating System :: Unix
Classifier: Operating System :: MacOS :: MacOS X
Classifier: Operating System :: Microsoft :: Windows
License-File: LICENSE
